NLPLAB/__init__.py
NLPLABNMIT-0.1.dist-info/LICENSE.txt
NLPLABNMIT-0.1.dist-info/METADATA
NLPLABNMIT-0.1.dist-info/WHEEL
NLPLABNMIT-0.1.dist-info/top_level.txt
NLPLABNMIT-0.1.dist-info/RECORD
