Metadata-Version: 2.1
Name: NLPLABNMIT
Version: 0.1
Summary: Lab programs of AIML lab
Author: Subhojeet
Author-email: chakrabortysubhojeet01@gmail.com
Classifier: Programming Language :: Python :: 3
Classifier: License :: OSI Approved :: MIT License
Classifier: Operating System :: OS Independent
License-File: LICENSE.txt
